iciflaskn/__init__.py
iciflaskn/auth.py
iciflaskn/config.py
iciflaskn/routes.py
iciflaskn-0.1.0.dist-info/LICENSE
iciflaskn-0.1.0.dist-info/METADATA
iciflaskn-0.1.0.dist-info/WHEEL
iciflaskn-0.1.0.dist-info/RECORD
