Metadata-Version: 2.1
Name: iciflaskn
Version: 0.1.0
Summary: A configurable flask blueprint providing authentication via ICICLE Tapis OAuth2
Author: Joe Stubbs
Author-email: joestubbs5@gmail.com
Requires-Python: >=3.8,<4.0
Classifier: Programming Language :: Python :: 3
Classifier: Programming Language :: Python :: 3.8
Classifier: Programming Language :: Python :: 3.9
Classifier: Programming Language :: Python :: 3.10
Classifier: Programming Language :: Python :: 3.11
Requires-Dist: flask (>=2.3.2,<3.0.0)
Requires-Dist: requests (>=2.31.0,<3.0.0)
Requires-Dist: tapipy (>=1.4.1,<2.0.0)
